{
    "ABEV": {
        "triggers": [],
        "trades": [],
        "totals": {
            "assetProfile": {
                "address1": "Rua Dr. Renato Paes de Barros, 1017",
                "address2": "3rd Floor",
                "city": "S\u00e3o Paulo",
                "state": "SP",
                "zip": "04530-001",
                "country": "Brazil",
                "phone": "55 11 2122 1414",
                "website": "https://www.ambev.com.br",
                "industry": "Beverages\u2014Brewers",
                "sector": "Consumer Defensive",
                "longBusinessSummary": "Ambev S.A., through its subsidiaries, engages in the production, distribution, and sale of beer, draft beer, carbonated soft drinks, malt and food, other alcoholic beverages, and non-alcoholic and non-carbonated products in Brazil, Central America and Caribbean, Latin America South, and Canada. It offers beer primarily under the Skol, Brahma, Antarctica, Brahva, Budweiser, Bud Light, Beck, Leffe, Hoegaarden, Balboa ICE, Balboa, Atlas Golden Light, Atlas, Bucanero, Cristal, Mayabe, Presidente, Presidente Light, Brahma Light, Bohemia, The One, Corona, Modelo Especial, Stella Artois, Quilmes Cl\u00e1sica, Pace\u00f1a, Taqui\u00f1a, Huari, Becker, Cusque\u00f1a, Michelob Ultra, Busch, Pilsen, Ouro Fino, Bud 66, Banks, Deputy, Patricia, Labatt Blue, Alexander Keith's, and Kokanee brands. The company also provides carbonated soft drinks, bottled water, isotonic beverages, energy drinks, coconut water, powdered and natural juices, and ready-to-drink teas under the Guaran\u00e1 Antarctica, Gatorade, H2OH!, Pepsi Black, Lipton Iced Tea, Fusion, Pepsi-Cola, Canada Dry, Squirt, Red Rock, Red Bull, Seven Up, Nutrl, Bud Light Seltzer, Palm Bay, and Mike's brands. It offers its products through a network of third-party distributors and a direct distribution system. The company was founded in 1885 and is headquartered in S\u00e3o Paulo, Brazil. Ambev S.A. is a subsidiary of Interbrew International B.V.",
                "fullTimeEmployees": 43000,
                "companyOfficers": [
                    {
                        "maxAge": 1,
                        "name": "Mr. Jean Jereissati Neto",
                        "age": 49,
                        "title": "CEO & Member of Executive Board",
                        "yearBorn": 1974,
                        "exercisedValue": 0,
                        "unexercisedValue": 0
                    },
                    {
                        "maxAge": 1,
                        "name": "Mr. Lucas Machado Lira",
                        "age": 46,
                        "title": "Member of Board of Executive Officers, Chief Financial & IR and Shared Services Officer",
                        "yearBorn": 1977,
                        "exercisedValue": 0,
                        "unexercisedValue": 0
                    },
                    {
                        "maxAge": 1,
                        "name": "Mr. Eduardo Braga Cavalcanti de Lacerda",
                        "age": 46,
                        "title": "VP Officer of Commercial & Member of Executive Board of Officers",
                        "yearBorn": 1977,
                        "exercisedValue": 0,
                        "unexercisedValue": 0
                    },
                    {
                        "maxAge": 1,
                        "name": "Mr. Ricardo Morais Pereira de Melo",
                        "age": 51,
                        "title": "VP Officer of People and Management & Member of Executive Board of Officers",
                        "yearBorn": 1972,
                        "exercisedValue": 0,
                        "unexercisedValue": 0
                    },
                    {
                        "maxAge": 1,
                        "name": "Ms. Leticia Rudge Barbosa Kina",
                        "age": 46,
                        "title": "VP Officer of Legal & Compliance, Member of Executive Board of Officers and Secretary",
                        "yearBorn": 1977,
                        "exercisedValue": 0,
                        "unexercisedValue": 0
                    },
                    {
                        "maxAge": 1,
                        "name": "Mr. Paulo Andr\u00e9 Zagman",
                        "age": 46,
                        "title": "VP Officer of Logistics & Member of Executive Board of Officers",
                        "yearBorn": 1977,
                        "exercisedValue": 0,
                        "unexercisedValue": 0
                    },
                    {
                        "maxAge": 1,
                        "name": "Mr. Eduardo Eiji Horai",
                        "age": 37,
                        "title": "VP Officer of Information Technology & Member of Board of Executive Officers",
                        "yearBorn": 1986,
                        "exercisedValue": 0,
                        "unexercisedValue": 0
                    },
                    {
                        "maxAge": 1,
                        "name": "Mr. Daniel Wakswaser Cordeiro",
                        "age": 38,
                        "title": "VP Officer of Marketing & Member of Executive Board of Officers",
                        "yearBorn": 1985,
                        "exercisedValue": 0,
                        "unexercisedValue": 0
                    },
                    {
                        "maxAge": 1,
                        "name": "Mr. Valdecir  Duarte",
                        "age": 42,
                        "title": "Industrial VP Officer & Member of Executive Board of Officers",
                        "yearBorn": 1981,
                        "exercisedValue": 0,
                        "unexercisedValue": 0
                    },
                    {
                        "maxAge": 1,
                        "name": "Ms. Daniela Gavranic Cachich",
                        "age": 50,
                        "title": "Beyond Beer VP Officer & Member of Board of Executive Officer",
                        "yearBorn": 1973,
                        "exercisedValue": 0,
                        "unexercisedValue": 0
                    }
                ],
                "auditRisk": 1,
                "boardRisk": 3,
                "compensationRisk": 9,
                "shareHolderRightsRisk": 8,
                "overallRisk": 5,
                "governanceEpochDate": "2024-06-30 19:00:00",
                "maxAge": 86400
            },
            "recommendationTrend": {
                "trend": [
                    {
                        "period": "0m",
                        "strongBuy": 0,
                        "buy": 3,
                        "hold": 5,
                        "sell": 0,
                        "strongSell": 0
                    },
                    {
                        "period": "-1m",
                        "strongBuy": 2,
                        "buy": 3,
                        "hold": 3,
                        "sell": 1,
                        "strongSell": 0
                    },
                    {
                        "period": "-2m",
                        "strongBuy": 2,
                        "buy": 3,
                        "hold": 3,
                        "sell": 1,
                        "strongSell": 0
                    },
                    {
                        "period": "-3m",
                        "strongBuy": 0,
                        "buy": 3,
                        "hold": 4,
                        "sell": 0,
                        "strongSell": 0
                    }
                ],
                "maxAge": 86400
            },
            "cashflowStatementHistory": {
                "cashflowStatements": [
                    {
                        "maxAge": 1,
                        "endDate": "2023-12-31",
                        "netIncome": 14501944000
                    },
                    {
                        "maxAge": 1,
                        "endDate": "2022-12-31",
                        "netIncome": 14457943000
                    },
                    {
                        "maxAge": 1,
                        "endDate": "2021-12-31",
                        "netIncome": 12670968000
                    },
                    {
                        "maxAge": 1,
                        "endDate": "2020-12-31",
                        "netIncome": 11379394000
                    }
                ],
                "maxAge": 86400
            },
            "indexTrend": {
                "maxAge": 1,
                "symbol": "SP5",
                "peRatio": 19.8083,
                "pegRatio": 1.63808,
                "estimates": [
                    {
                        "period": "0q",
                        "growth": 0.056999996
                    },
                    {
                        "period": "+1q",
                        "growth": 0.096
                    },
                    {
                        "period": "0y",
                        "growth": 0.036
                    },
                    {
                        "period": "+1y",
                        "growth": 0.123
                    },
                    {
                        "period": "+5y",
                        "growth": 0.114567004
                    },
                    {
                        "period": "-5y"
                    }
                ]
            },
            "defaultKeyStatistics": {
                "maxAge": 1,
                "priceHint": 4,
                "enterpriseValue": 24535537664,
                "forwardPE": 11.31579,
                "profitMargins": 0.18247,
                "floatShares": 4392805281,
                "sharesOutstanding": 15726199808,
                "sharesShort": 33492090,
                "sharesShortPriorMonth": 10356742,
                "sharesShortPreviousMonthDate": "2024-05-30 19:00:00",
                "dateShortInterest": "2024-06-27 19:00:00",
                "sharesPercentSharesOut": 0.0021,
                "heldPercentInsiders": 5e-05,
                "heldPercentInstitutions": 0.08653,
                "shortRatio": 1.42,
                "beta": 0.536,
                "category": null,
                "bookValue": 5.499,
                "priceToBook": 0.39098018,
                "fundFamily": null,
                "legalType": null,
                "lastFiscalYearEnd": "2023-12-30 18:00:00",
                "nextFiscalYearEnd": "2024-12-30 18:00:00",
                "mostRecentQuarter": "2024-03-30 19:00:00",
                "earningsQuarterlyGrowth": 0.0,
                "netIncomeToCommon": 14502644736,
                "trailingEps": 0.17,
                "forwardEps": 0.19,
                "pegRatio": 3.21,
                "lastSplitFactor": "5:1",
                "lastSplitDate": "2013-11-10 18:00:00",
                "enterpriseToRevenue": 0.309,
                "enterpriseToEbitda": 1.056
            },
            "industryTrend": {
                "maxAge": 1,
                "symbol": null,
                "estimates": []
            },
            "quoteType": {
                "exchange": "NYQ",
                "quoteType": "EQUITY",
                "symbol": "ABEV",
                "underlyingSymbol": "ABEV",
                "shortName": "Ambev S.A.",
                "longName": "Ambev S.A.",
                "firstTradeDateEpochUtc": "1997-03-05 08:30:00",
                "timeZoneFullName": "America/New_York",
                "timeZoneShortName": "EDT",
                "uuid": "ce165950-0d52-3418-aa61-a6b5ff802566",
                "gmtOffSetMilliseconds": -14400000,
                "maxAge": 1
            },
            "incomeStatementHistory": {
                "incomeStatementHistory": [
                    {
                        "maxAge": 1,
                        "endDate": "2023-12-31",
                        "totalRevenue": 79736856000,
                        "costOfRevenue": 0,
                        "grossProfit": 0,
                        "researchDevelopment": {},
                        "sellingGeneralAdministrative": {},
                        "nonRecurring": {},
                        "otherOperatingExpenses": {},
                        "totalOperatingExpenses": 0,
                        "operatingIncome": {},
                        "totalOtherIncomeExpenseNet": {},
                        "ebit": 0,
                        "interestExpense": {},
                        "incomeBeforeTax": {},
                        "incomeTaxExpense": 0,
                        "minorityInterest": {},
                        "netIncomeFromContinuingOps": {},
                        "discontinuedOperations": {},
                        "extraordinaryItems": {},
                        "effectOfAccountingCharges": {},
                        "otherItems": {},
                        "netIncome": 14501944000,
                        "netIncomeApplicableToCommonShares": {}
                    },
                    {
                        "maxAge": 1,
                        "endDate": "2022-12-31",
                        "totalRevenue": 79708827000,
                        "costOfRevenue": 0,
                        "grossProfit": 0,
                        "researchDevelopment": {},
                        "sellingGeneralAdministrative": {},
                        "nonRecurring": {},
                        "otherOperatingExpenses": {},
                        "totalOperatingExpenses": 0,
                        "operatingIncome": {},
                        "totalOtherIncomeExpenseNet": {},
                        "ebit": 0,
                        "interestExpense": {},
                        "incomeBeforeTax": {},
                        "incomeTaxExpense": 0,
                        "minorityInterest": {},
                        "netIncomeFromContinuingOps": {},
                        "discontinuedOperations": {},
                        "extraordinaryItems": {},
                        "effectOfAccountingCharges": {},
                        "otherItems": {},
                        "netIncome": 14457943000,
                        "netIncomeApplicableToCommonShares": {}
                    },
                    {
                        "maxAge": 1,
                        "endDate": "2021-12-31",
                        "totalRevenue": 72854344000,
                        "costOfRevenue": 0,
                        "grossProfit": 0,
                        "researchDevelopment": {},
                        "sellingGeneralAdministrative": {},
                        "nonRecurring": {},
                        "otherOperatingExpenses": {},
                        "totalOperatingExpenses": 0,
                        "operatingIncome": {},
                        "totalOtherIncomeExpenseNet": {},
                        "ebit": 0,
                        "interestExpense": {},
                        "incomeBeforeTax": {},
                        "incomeTaxExpense": 0,
                        "minorityInterest": {},
                        "netIncomeFromContinuingOps": {},
                        "discontinuedOperations": {},
                        "extraordinaryItems": {},
                        "effectOfAccountingCharges": {},
                        "otherItems": {},
                        "netIncome": 12670968000,
                        "netIncomeApplicableToCommonShares": {}
                    },
                    {
                        "maxAge": 1,
                        "endDate": "2020-12-31",
                        "totalRevenue": 58378995000,
                        "costOfRevenue": 0,
                        "grossProfit": 0,
                        "researchDevelopment": {},
                        "sellingGeneralAdministrative": {},
                        "nonRecurring": {},
                        "otherOperatingExpenses": {},
                        "totalOperatingExpenses": 0,
                        "operatingIncome": {},
                        "totalOtherIncomeExpenseNet": {},
                        "ebit": 0,
                        "interestExpense": {},
                        "incomeBeforeTax": {},
                        "incomeTaxExpense": 0,
                        "minorityInterest": {},
                        "netIncomeFromContinuingOps": {},
                        "discontinuedOperations": {},
                        "extraordinaryItems": {},
                        "effectOfAccountingCharges": {},
                        "otherItems": {},
                        "netIncome": 11379394000,
                        "netIncomeApplicableToCommonShares": {}
                    }
                ],
                "maxAge": 86400
            },
            "fundOwnership": {
                "ownershipList": [
                    {
                        "maxAge": 1,
                        "reportDate": "2023-07-31",
                        "organization": "First Eagle Global Fund",
                        "pctHeld": 0.0095,
                        "position": 149620059,
                        "value": 466814584
                    },
                    {
                        "maxAge": 1,
                        "reportDate": "2023-07-31",
                        "organization": "First Eagle Overseas Fund",
                        "pctHeld": 0.0047,
                        "position": 74789315,
                        "value": 233342662
                    },
                    {
                        "maxAge": 1,
                        "reportDate": "2023-07-31",
                        "organization": "Harding, Loevner Funds, Inc-International Equity Portfolio",
                        "pctHeld": 0.004,
                        "position": 62883859,
                        "value": 196197640
                    },
                    {
                        "maxAge": 1,
                        "reportDate": "2023-06-30",
                        "organization": "Janus Henderson Global Equity Income Fund",
                        "pctHeld": 0.0027,
                        "position": 41853468,
                        "value": 133094028
                    },
                    {
                        "maxAge": 1,
                        "reportDate": "2023-05-31",
                        "organization": "MFS Series Trust X-MFS Emerging Markets Equity Fund",
                        "pctHeld": 0.0018000001,
                        "position": 29127819,
                        "value": 81266615
                    },
                    {
                        "maxAge": 1,
                        "reportDate": "2023-07-31",
                        "organization": "Vanguard International Value Fund",
                        "pctHeld": 0.0017,
                        "position": 27553800,
                        "value": 85967856
                    },
                    {
                        "maxAge": 1,
                        "reportDate": "2023-07-31",
                        "organization": "Financial Investors Tr-Seafarer Overseas Growth & Income Fd",
                        "pctHeld": 0.001,
                        "position": 16000000,
                        "value": 49920000
                    },
                    {
                        "maxAge": 1,
                        "reportDate": "2023-08-31",
                        "organization": "iShares Latin America 40 ETF",
                        "pctHeld": 0.00090000004,
                        "position": 14290433,
                        "value": 39584499
                    },
                    {
                        "maxAge": 1,
                        "reportDate": "2023-06-30",
                        "organization": "Advisers Investment Tr-JOHCM Emerging Markets Opportunities Fd",
                        "pctHeld": 0.0007,
                        "position": 10792224,
                        "value": 34319272
                    },
                    {
                        "maxAge": 1,
                        "reportDate": "2023-07-31",
                        "organization": "Blackrock Emerging Markets Fund",
                        "pctHeld": 0.0005,
                        "position": 7633140,
                        "value": 23815396
                    }
                ],
                "maxAge": 1
            },
            "summaryDetail": {
                "maxAge": 1,
                "priceHint": 4,
                "previousClose": 2.14,
                "open": 2.15,
                "dayLow": 2.12,
                "dayHigh": 2.16,
                "regularMarketPreviousClose": 2.14,
                "regularMarketOpen": 2.15,
                "regularMarketDayLow": 2.12,
                "regularMarketDayHigh": 2.16,
                "dividendRate": 0.15,
                "dividendYield": 0.070199996,
                "exDividendDate": "2023-12-21 18:00:00",
                "payoutRatio": 0.8001,
                "fiveYearAvgDividendYield": 3.74,
                "beta": 0.536,
                "trailingPE": 12.647059,
                "forwardPE": 11.31579,
                "volume": 17546510,
                "regularMarketVolume": 17546510,
                "averageVolume": 17569580,
                "averageVolume10days": 20526410,
                "averageDailyVolume10Day": 20526410,
                "bid": 2.12,
                "ask": 2.15,
                "bidSize": 308800,
                "askSize": 46000,
                "marketCap": 33811331072,
                "fiftyTwoWeekLow": 2.01,
                "fiftyTwoWeekHigh": 3.22,
                "priceToSalesTrailing12Months": 0.4253992,
                "fiftyDayAverage": 2.21,
                "twoHundredDayAverage": 2.5079,
                "trailingAnnualDividendRate": 0.73,
                "trailingAnnualDividendYield": 0.3411215,
                "currency": "USD",
                "fromCurrency": null,
                "lastMarket": null,
                "algorithm": null,
                "tradeable": false
            },
            "insiderHolders": {
                "holders": [],
                "maxAge": 1
            },
            "calendarEvents": {
                "maxAge": 1,
                "earnings": {
                    "earningsDate": [
                        "2024-07-31 19:00:S"
                    ],
                    "earningsAverage": 0.03,
                    "earningsLow": 0.03,
                    "earningsHigh": 0.04,
                    "revenueAverage": 3706850000,
                    "revenueLow": 3660700000,
                    "revenueHigh": 3753000000
                },
                "exDividendDate": "2023-12-21 18:00:00",
                "dividendDate": "2024-01-04 18:00:00"
            },
            "upgradeDowngradeHistory": {
                "history": [
                    {
                        "epochGradeDate": "2023-05-23 19:00:00",
                        "firm": "Bernstein",
                        "toGrade": "Outperform",
                        "fromGrade": "",
                        "action": "init"
                    },
                    {
                        "epochGradeDate": "2022-07-12 19:00:00",
                        "firm": "JP Morgan",
                        "toGrade": "Overweight",
                        "fromGrade": "Neutral",
                        "action": "up"
                    },
                    {
                        "epochGradeDate": "2021-11-02 19:00:00",
                        "firm": "B of A Securities",
                        "toGrade": "Neutral",
                        "fromGrade": "Underperform",
                        "action": "up"
                    },
                    {
                        "epochGradeDate": "2021-10-05 19:00:00",
                        "firm": "Barclays",
                        "toGrade": "Overweight",
                        "fromGrade": "Equal-Weight",
                        "action": "up"
                    },
                    {
                        "epochGradeDate": "2021-06-16 19:00:00",
                        "firm": "Barclays",
                        "toGrade": "Equal-Weight",
                        "fromGrade": "Underweight",
                        "action": "up"
                    },
                    {
                        "epochGradeDate": "2021-05-19 19:00:00",
                        "firm": "Itau BBA",
                        "toGrade": "Market Perform",
                        "fromGrade": "Outperform",
                        "action": "down"
                    },
                    {
                        "epochGradeDate": "2021-01-12 18:00:00",
                        "firm": "Bradesco",
                        "toGrade": "Underperform",
                        "fromGrade": "Neutral",
                        "action": "down"
                    },
                    {
                        "epochGradeDate": "2020-11-02 18:00:00",
                        "firm": "Citigroup",
                        "toGrade": "Buy",
                        "fromGrade": "Neutral",
                        "action": "up"
                    },
                    {
                        "epochGradeDate": "2020-03-23 19:00:00",
                        "firm": "JP Morgan",
                        "toGrade": "Underweight",
                        "fromGrade": "Neutral",
                        "action": "down"
                    },
                    {
                        "epochGradeDate": "2019-12-02 18:00:00",
                        "firm": "Barclays",
                        "toGrade": "Underweight",
                        "fromGrade": "Equal-Weight",
                        "action": "down"
                    },
                    {
                        "epochGradeDate": "2019-11-14 18:00:00",
                        "firm": "UBS",
                        "toGrade": "Sell",
                        "fromGrade": "",
                        "action": "main"
                    },
                    {
                        "epochGradeDate": "2019-08-26 19:00:00",
                        "firm": "Barclays",
                        "toGrade": "Equal-Weight",
                        "fromGrade": "Overweight",
                        "action": "down"
                    },
                    {
                        "epochGradeDate": "2019-07-25 19:00:00",
                        "firm": "JP Morgan",
                        "toGrade": "Neutral",
                        "fromGrade": "Underweight",
                        "action": "up"
                    },
                    {
                        "epochGradeDate": "2018-10-24 19:00:00",
                        "firm": "B of A Securities",
                        "toGrade": "Underperform",
                        "fromGrade": "Neutral",
                        "action": "down"
                    },
                    {
                        "epochGradeDate": "2018-07-26 19:00:00",
                        "firm": "Barclays",
                        "toGrade": "Overweight",
                        "fromGrade": "Equal-Weight",
                        "action": "up"
                    },
                    {
                        "epochGradeDate": "2018-05-21 19:00:00",
                        "firm": "JP Morgan",
                        "toGrade": "Overweight",
                        "fromGrade": "Overweight",
                        "action": "main"
                    },
                    {
                        "epochGradeDate": "2018-04-08 19:00:00",
                        "firm": "JP Morgan",
                        "toGrade": "Overweight",
                        "fromGrade": "Overweight",
                        "action": "main"
                    },
                    {
                        "epochGradeDate": "2017-10-26 19:00:00",
                        "firm": "Barclays",
                        "toGrade": "Equal-Weight",
                        "fromGrade": "",
                        "action": "main"
                    },
                    {
                        "epochGradeDate": "2017-09-11 19:00:00",
                        "firm": "Credit Suisse",
                        "toGrade": "Outperform",
                        "fromGrade": "Neutral",
                        "action": "up"
                    },
                    {
                        "epochGradeDate": "2016-11-09 18:00:00",
                        "firm": "JP Morgan",
                        "toGrade": "Overweight",
                        "fromGrade": "Neutral",
                        "action": "up"
                    },
                    {
                        "epochGradeDate": "2016-11-02 19:00:00",
                        "firm": "Barclays",
                        "toGrade": "Equal-Weight",
                        "fromGrade": "",
                        "action": "init"
                    },
                    {
                        "epochGradeDate": "2016-08-17 19:00:00",
                        "firm": "Morgan Stanley",
                        "toGrade": "Equal-Weight",
                        "fromGrade": "Overweight",
                        "action": "down"
                    },
                    {
                        "epochGradeDate": "2016-05-04 19:00:00",
                        "firm": "JP Morgan",
                        "toGrade": "Neutral",
                        "fromGrade": "Overweight",
                        "action": "down"
                    },
                    {
                        "epochGradeDate": "2015-05-31 19:00:00",
                        "firm": "JP Morgan",
                        "toGrade": "Overweight",
                        "fromGrade": "Neutral",
                        "action": "up"
                    },
                    {
                        "epochGradeDate": "2014-12-16 18:00:00",
                        "firm": "Morgan Stanley",
                        "toGrade": "Overweight",
                        "fromGrade": "",
                        "action": "main"
                    },
                    {
                        "epochGradeDate": "2014-11-10 18:00:00",
                        "firm": "JP Morgan",
                        "toGrade": "Neutral",
                        "fromGrade": "",
                        "action": "main"
                    },
                    {
                        "epochGradeDate": "2014-06-08 19:00:00",
                        "firm": "Barclays",
                        "toGrade": "Overweight",
                        "fromGrade": "",
                        "action": "main"
                    },
                    {
                        "epochGradeDate": "2014-06-02 19:00:00",
                        "firm": "JP Morgan",
                        "toGrade": "Overweight",
                        "fromGrade": "",
                        "action": "main"
                    },
                    {
                        "epochGradeDate": "2014-04-30 19:00:00",
                        "firm": "JP Morgan",
                        "toGrade": "Overweight",
                        "fromGrade": "",
                        "action": "main"
                    },
                    {
                        "epochGradeDate": "2014-01-06 18:00:00",
                        "firm": "Morgan Stanley",
                        "toGrade": "Overweight",
                        "fromGrade": "Equal-weight",
                        "action": "up"
                    },
                    {
                        "epochGradeDate": "2013-01-09 18:00:00",
                        "firm": "JP Morgan",
                        "toGrade": "Overweight",
                        "fromGrade": "",
                        "action": "main"
                    },
                    {
                        "epochGradeDate": "2012-08-20 19:00:00",
                        "firm": "Deutsche Bank",
                        "toGrade": "Hold",
                        "fromGrade": "",
                        "action": "main"
                    },
                    {
                        "epochGradeDate": "2012-07-19 19:00:00",
                        "firm": "Citigroup",
                        "toGrade": "Buy",
                        "fromGrade": "",
                        "action": "init"
                    }
                ],
                "maxAge": 86400
            },
            "price": {
                "maxAge": 1,
                "preMarketSource": "FREE_REALTIME",
                "postMarketChangePercent": -0.000232652,
                "postMarketChange": -0.000500202,
                "postMarketTime": "2024-07-12 18:57:44",
                "postMarketPrice": 2.1495,
                "postMarketSource": "FREE_REALTIME",
                "regularMarketChangePercent": 0.0046728924,
                "regularMarketChange": 0.00999999,
                "regularMarketTime": "2024-07-12 15:00:01",
                "priceHint": 4,
                "regularMarketPrice": 2.15,
                "regularMarketDayHigh": 2.16,
                "regularMarketDayLow": 2.12,
                "regularMarketVolume": 17546510,
                "averageDailyVolume10Day": 20526410,
                "averageDailyVolume3Month": 17569580,
                "regularMarketPreviousClose": 2.14,
                "regularMarketSource": "DELAYED",
                "regularMarketOpen": 2.15,
                "exchange": "NYQ",
                "exchangeName": "NYSE",
                "exchangeDataDelayedBy": 0,
                "marketState": "CLOSED",
                "quoteType": "EQUITY",
                "symbol": "ABEV",
                "underlyingSymbol": null,
                "shortName": "Ambev S.A.",
                "longName": "Ambev S.A.",
                "currency": "USD",
                "quoteSourceName": "Nasdaq Real Time Price",
                "currencySymbol": "$",
                "fromCurrency": null,
                "lastMarket": null,
                "marketCap": 33811331072
            },
            "balanceSheetHistory": {
                "balanceSheetStatements": [
                    {
                        "maxAge": 1,
                        "endDate": "2023-12-31"
                    },
                    {
                        "maxAge": 1,
                        "endDate": "2022-12-31"
                    },
                    {
                        "maxAge": 1,
                        "endDate": "2021-12-31"
                    },
                    {
                        "maxAge": 1,
                        "endDate": "2020-12-31"
                    }
                ],
                "maxAge": 86400
            },
            "earningsTrend": {
                "trend": [
                    {
                        "maxAge": 1,
                        "period": "0q",
                        "endDate": "2024-06-30",
                        "growth": 0.0,
                        "earningsEstimate": {
                            "avg": 0.03,
                            "low": 0.03,
                            "high": 0.04,
                            "yearAgoEps": 0.03,
                            "numberOfAnalysts": 4,
                            "growth": 0.0
                        },
                        "revenueEstimate": {
                            "avg": 3706850000,
                            "low": 3660700000,
                            "high": 3753000000,
                            "numberOfAnalysts": 2,
                            "yearAgoRevenue": 3821080000,
                            "growth": -0.03
                        },
                        "epsTrend": {
                            "current": 0.03,
                            "7daysAgo": 0.03,
                            "30daysAgo": 0.03,
                            "60daysAgo": 0.03,
                            "90daysAgo": 0.03
                        },
                        "epsRevisions": {
                            "upLast7days": 0,
                            "upLast30days": 0,
                            "downLast30days": 0,
                            "downLast90days": {}
                        }
                    },
                    {
                        "maxAge": 1,
                        "period": "+1q",
                        "endDate": "2024-09-30",
                        "growth": -0.2,
                        "earningsEstimate": {
                            "avg": 0.04,
                            "low": 0.04,
                            "high": 0.05,
                            "yearAgoEps": 0.05,
                            "numberOfAnalysts": 4,
                            "growth": -0.2
                        },
                        "revenueEstimate": {
                            "avg": 4056390000,
                            "low": 3783780000,
                            "high": 4329000000,
                            "numberOfAnalysts": 2,
                            "yearAgoRevenue": 4239400000,
                            "growth": -0.043
                        },
                        "epsTrend": {
                            "current": 0.04,
                            "7daysAgo": 0.04,
                            "30daysAgo": 0.04,
                            "60daysAgo": 0.04,
                            "90daysAgo": 0.04
                        },
                        "epsRevisions": {
                            "upLast7days": 0,
                            "upLast30days": 0,
                            "downLast30days": 0,
                            "downLast90days": {}
                        }
                    },
                    {
                        "maxAge": 1,
                        "period": "0y",
                        "endDate": "2024-12-31",
                        "growth": -0.053000003,
                        "earningsEstimate": {
                            "avg": 0.18,
                            "low": 0.17,
                            "high": 0.19,
                            "yearAgoEps": 0.19,
                            "numberOfAnalysts": 5,
                            "growth": -0.053000003
                        },
                        "revenueEstimate": {
                            "avg": 16050900000,
                            "low": 15495700000,
                            "high": 16873000000,
                            "numberOfAnalysts": 4,
                            "yearAgoRevenue": 15966200000,
                            "growth": 0.005
                        },
                        "epsTrend": {
                            "current": 0.18,
                            "7daysAgo": 0.18,
                            "30daysAgo": 0.18,
                            "60daysAgo": 0.18,
                            "90daysAgo": 0.17
                        },
                        "epsRevisions": {
                            "upLast7days": 0,
                            "upLast30days": 0,
                            "downLast30days": 0,
                            "downLast90days": {}
                        }
                    },
                    {
                        "maxAge": 1,
                        "period": "+1y",
                        "endDate": "2025-12-31",
                        "growth": 0.055999998,
                        "earningsEstimate": {
                            "avg": 0.19,
                            "low": 0.17,
                            "high": 0.2,
                            "yearAgoEps": 0.18,
                            "numberOfAnalysts": 5,
                            "growth": 0.055999998
                        },
                        "revenueEstimate": {
                            "avg": 16872100000,
                            "low": 16320000000,
                            "high": 17518000000,
                            "numberOfAnalysts": 4,
                            "yearAgoRevenue": 16050900000,
                            "growth": 0.051
                        },
                        "epsTrend": {
                            "current": 0.19,
                            "7daysAgo": 0.19,
                            "30daysAgo": 0.19,
                            "60daysAgo": 0.19,
                            "90daysAgo": 0.19
                        },
                        "epsRevisions": {
                            "upLast7days": 0,
                            "upLast30days": 0,
                            "downLast30days": 0,
                            "downLast90days": {}
                        }
                    },
                    {
                        "maxAge": 1,
                        "period": "+5y",
                        "endDate": null,
                        "growth": 0.037,
                        "earningsEstimate": {
                            "avg": {},
                            "low": {},
                            "high": {},
                            "yearAgoEps": {},
                            "numberOfAnalysts": {},
                            "growth": {}
                        },
                        "revenueEstimate": {
                            "avg": {},
                            "low": {},
                            "high": {},
                            "numberOfAnalysts": {},
                            "yearAgoRevenue": {},
                            "growth": {}
                        },
                        "epsTrend": {
                            "current": {},
                            "7daysAgo": {},
                            "30daysAgo": {},
                            "60daysAgo": {},
                            "90daysAgo": {}
                        },
                        "epsRevisions": {
                            "upLast7days": {},
                            "upLast30days": {},
                            "downLast30days": {},
                            "downLast90days": {}
                        }
                    },
                    {
                        "maxAge": 1,
                        "period": "-5y",
                        "endDate": null,
                        "growth": 0.06999,
                        "earningsEstimate": {
                            "avg": {},
                            "low": {},
                            "high": {},
                            "yearAgoEps": {},
                            "numberOfAnalysts": {},
                            "growth": {}
                        },
                        "revenueEstimate": {
                            "avg": {},
                            "low": {},
                            "high": {},
                            "numberOfAnalysts": {},
                            "yearAgoRevenue": {},
                            "growth": {}
                        },
                        "epsTrend": {
                            "current": {},
                            "7daysAgo": {},
                            "30daysAgo": {},
                            "60daysAgo": {},
                            "90daysAgo": {}
                        },
                        "epsRevisions": {
                            "upLast7days": {},
                            "upLast30days": {},
                            "downLast30days": {},
                            "downLast90days": {}
                        }
                    }
                ],
                "maxAge": 1
            },
            "institutionOwnership": {
                "ownershipList": [
                    {
                        "maxAge": 1,
                        "reportDate": "2023-06-30",
                        "organization": "First Eagle Investment Management, LLC",
                        "pctHeld": 0.0198,
                        "position": 311641579,
                        "value": 991020221
                    },
                    {
                        "maxAge": 1,
                        "reportDate": "2023-06-30",
                        "organization": "Harding Loevner LLC",
                        "pctHeld": 0.0074,
                        "position": 116526981,
                        "value": 370555799
                    },
                    {
                        "maxAge": 1,
                        "reportDate": "2023-06-30",
                        "organization": "Westwood Global Investments, LLC",
                        "pctHeld": 0.0066000004,
                        "position": 103953232,
                        "value": 330571277
                    },
                    {
                        "maxAge": 1,
                        "reportDate": "2023-06-30",
                        "organization": "Sprucegrove Investment Management Ltd",
                        "pctHeld": 0.0050999997,
                        "position": 79811452,
                        "value": 253800417
                    },
                    {
                        "maxAge": 1,
                        "reportDate": "2023-06-30",
                        "organization": "Blackrock Inc.",
                        "pctHeld": 0.0037,
                        "position": 58604106,
                        "value": 186361057
                    },
                    {
                        "maxAge": 1,
                        "reportDate": "2023-06-30",
                        "organization": "Janus Henderson Group PLC",
                        "pctHeld": 0.0032,
                        "position": 49858560,
                        "value": 158550220
                    },
                    {
                        "maxAge": 1,
                        "reportDate": "2023-06-30",
                        "organization": "Ruffer LLP",
                        "pctHeld": 0.0029,
                        "position": 44930005,
                        "value": 142877415
                    },
                    {
                        "maxAge": 1,
                        "reportDate": "2023-09-30",
                        "organization": "Ninety One UK Ltd",
                        "pctHeld": 0.0026,
                        "position": 41593127,
                        "value": 107310267
                    },
                    {
                        "maxAge": 1,
                        "reportDate": "2023-06-30",
                        "organization": "JP Morgan Chase & Company",
                        "pctHeld": 0.0025,
                        "position": 39008393,
                        "value": 124046689
                    },
                    {
                        "maxAge": 1,
                        "reportDate": "2023-06-30",
                        "organization": "Goldman Sachs Group Inc",
                        "pctHeld": 0.0023,
                        "position": 35455537,
                        "value": 112748607
                    }
                ],
                "maxAge": 1
            },
            "majorHoldersBreakdown": {
                "maxAge": 1,
                "insidersPercentHeld": 5e-05,
                "institutionsPercentHeld": 0.08653,
                "institutionsFloatPercentHeld": 0.08653,
                "institutionsCount": 456
            },
            "balanceSheetHistoryQuarterly": {
                "balanceSheetStatements": [
                    {
                        "maxAge": 1,
                        "endDate": "2024-03-31"
                    },
                    {
                        "maxAge": 1,
                        "endDate": "2023-12-31"
                    },
                    {
                        "maxAge": 1,
                        "endDate": "2023-09-30"
                    },
                    {
                        "maxAge": 1,
                        "endDate": "2023-06-30"
                    }
                ],
                "maxAge": 86400
            },
            "earningsHistory": {
                "history": [
                    {
                        "maxAge": 1,
                        "epsActual": 0.03,
                        "epsEstimate": 0.03,
                        "epsDifference": 0.0,
                        "surprisePercent": 0.0,
                        "quarter": "2023-06-30",
                        "period": "-4q"
                    },
                    {
                        "maxAge": 1,
                        "epsActual": 0.05,
                        "epsEstimate": 0.04,
                        "epsDifference": 0.01,
                        "surprisePercent": 0.25,
                        "quarter": "2023-09-30",
                        "period": "-3q"
                    },
                    {
                        "maxAge": 1,
                        "epsActual": 0.06,
                        "epsEstimate": 0.05,
                        "epsDifference": 0.01,
                        "surprisePercent": 0.2,
                        "quarter": "2023-12-31",
                        "period": "-2q"
                    },
                    {
                        "maxAge": 1,
                        "epsActual": 0.05,
                        "epsEstimate": 0.04,
                        "epsDifference": 0.01,
                        "surprisePercent": 0.25,
                        "quarter": "2024-03-31",
                        "period": "-1q"
                    }
                ],
                "maxAge": 86400
            },
            "summaryProfile": {
                "address1": "Rua Dr. Renato Paes de Barros, 1017",
                "address2": "3rd Floor",
                "city": "S\u00e3o Paulo",
                "state": "SP",
                "zip": "04530-001",
                "country": "Brazil",
                "phone": "55 11 2122 1414",
                "website": "https://www.ambev.com.br",
                "industry": "Beverages\u2014Brewers",
                "sector": "Consumer Defensive",
                "longBusinessSummary": "Ambev S.A., through its subsidiaries, engages in the production, distribution, and sale of beer, draft beer, carbonated soft drinks, malt and food, other alcoholic beverages, and non-alcoholic and non-carbonated products in Brazil, Central America and Caribbean, Latin America South, and Canada. It offers beer primarily under the Skol, Brahma, Antarctica, Brahva, Budweiser, Bud Light, Beck, Leffe, Hoegaarden, Balboa ICE, Balboa, Atlas Golden Light, Atlas, Bucanero, Cristal, Mayabe, Presidente, Presidente Light, Brahma Light, Bohemia, The One, Corona, Modelo Especial, Stella Artois, Quilmes Cl\u00e1sica, Pace\u00f1a, Taqui\u00f1a, Huari, Becker, Cusque\u00f1a, Michelob Ultra, Busch, Pilsen, Ouro Fino, Bud 66, Banks, Deputy, Patricia, Labatt Blue, Alexander Keith's, and Kokanee brands. The company also provides carbonated soft drinks, bottled water, isotonic beverages, energy drinks, coconut water, powdered and natural juices, and ready-to-drink teas under the Guaran\u00e1 Antarctica, Gatorade, H2OH!, Pepsi Black, Lipton Iced Tea, Fusion, Pepsi-Cola, Canada Dry, Squirt, Red Rock, Red Bull, Seven Up, Nutrl, Bud Light Seltzer, Palm Bay, and Mike's brands. It offers its products through a network of third-party distributors and a direct distribution system. The company was founded in 1885 and is headquartered in S\u00e3o Paulo, Brazil. Ambev S.A. is a subsidiary of Interbrew International B.V.",
                "fullTimeEmployees": 43000,
                "companyOfficers": [],
                "maxAge": 86400
            },
            "netSharePurchaseActivity": {
                "maxAge": 1,
                "period": "6m",
                "buyInfoCount": 0,
                "buyInfoShares": 0,
                "sellInfoCount": 0,
                "netInfoCount": 0,
                "netInfoShares": 0,
                "totalInsiderShares": 787382
            },
            "sectorTrend": {
                "maxAge": 1,
                "symbol": null,
                "estimates": []
            },
            "incomeStatementHistoryQuarterly": {
                "incomeStatementHistory": [
                    {
                        "maxAge": 1,
                        "endDate": "2024-03-31",
                        "totalRevenue": 20276297000,
                        "costOfRevenue": 0,
                        "grossProfit": 0,
                        "researchDevelopment": {},
                        "sellingGeneralAdministrative": {},
                        "nonRecurring": {},
                        "otherOperatingExpenses": {},
                        "totalOperatingExpenses": 0,
                        "operatingIncome": {},
                        "totalOtherIncomeExpenseNet": {},
                        "ebit": 0,
                        "interestExpense": {},
                        "incomeBeforeTax": {},
                        "incomeTaxExpense": 0,
                        "minorityInterest": {},
                        "netIncomeFromContinuingOps": {},
                        "discontinuedOperations": {},
                        "extraordinaryItems": {},
                        "effectOfAccountingCharges": {},
                        "otherItems": {},
                        "netIncome": 3700276000,
                        "netIncomeApplicableToCommonShares": {}
                    },
                    {
                        "maxAge": 1,
                        "endDate": "2023-12-31",
                        "totalRevenue": 19989234000,
                        "costOfRevenue": 0,
                        "grossProfit": 0,
                        "researchDevelopment": {},
                        "sellingGeneralAdministrative": {},
                        "nonRecurring": {},
                        "otherOperatingExpenses": {},
                        "totalOperatingExpenses": 0,
                        "operatingIncome": {},
                        "totalOtherIncomeExpenseNet": {},
                        "ebit": 0,
                        "interestExpense": {},
                        "incomeBeforeTax": {},
                        "incomeTaxExpense": 0,
                        "minorityInterest": {},
                        "netIncomeFromContinuingOps": {},
                        "discontinuedOperations": {},
                        "extraordinaryItems": {},
                        "effectOfAccountingCharges": {},
                        "otherItems": {},
                        "netIncome": 4387655000,
                        "netIncomeApplicableToCommonShares": {}
                    },
                    {
                        "maxAge": 1,
                        "endDate": "2023-09-30",
                        "totalRevenue": 20317765000,
                        "costOfRevenue": 0,
                        "grossProfit": 0,
                        "researchDevelopment": {},
                        "sellingGeneralAdministrative": {},
                        "nonRecurring": {},
                        "otherOperatingExpenses": {},
                        "totalOperatingExpenses": 0,
                        "operatingIncome": {},
                        "totalOtherIncomeExpenseNet": {},
                        "ebit": 0,
                        "interestExpense": {},
                        "incomeBeforeTax": {},
                        "incomeTaxExpense": 0,
                        "minorityInterest": {},
                        "netIncomeFromContinuingOps": {},
                        "discontinuedOperations": {},
                        "extraordinaryItems": {},
                        "effectOfAccountingCharges": {},
                        "otherItems": {},
                        "netIncome": 3911740000,
                        "netIncomeApplicableToCommonShares": {}
                    },
                    {
                        "maxAge": 1,
                        "endDate": "2023-06-30",
                        "totalRevenue": 18898114000,
                        "costOfRevenue": 0,
                        "grossProfit": 0,
                        "researchDevelopment": {},
                        "sellingGeneralAdministrative": {},
                        "nonRecurring": {},
                        "otherOperatingExpenses": {},
                        "totalOperatingExpenses": 0,
                        "operatingIncome": {},
                        "totalOtherIncomeExpenseNet": {},
                        "ebit": 0,
                        "interestExpense": {},
                        "incomeBeforeTax": {},
                        "incomeTaxExpense": 0,
                        "minorityInterest": {},
                        "netIncomeFromContinuingOps": {},
                        "discontinuedOperations": {},
                        "extraordinaryItems": {},
                        "effectOfAccountingCharges": {},
                        "otherItems": {},
                        "netIncome": 2502974000,
                        "netIncomeApplicableToCommonShares": {}
                    }
                ],
                "maxAge": 86400
            },
            "cashflowStatementHistoryQuarterly": {
                "cashflowStatements": [
                    {
                        "maxAge": 1,
                        "endDate": "2024-03-31",
                        "netIncome": 3700276000
                    },
                    {
                        "maxAge": 1,
                        "endDate": "2023-12-31",
                        "netIncome": 4387655000
                    },
                    {
                        "maxAge": 1,
                        "endDate": "2023-09-30",
                        "netIncome": 3911740000
                    },
                    {
                        "maxAge": 1,
                        "endDate": "2023-06-30",
                        "netIncome": 2502974000
                    }
                ],
                "maxAge": 86400
            },
            "earnings": {
                "maxAge": 86400,
                "earningsChart": {
                    "quarterly": [
                        {
                            "date": "2Q2023",
                            "actual": 0.03,
                            "estimate": 0.03
                        },
                        {
                            "date": "3Q2023",
                            "actual": 0.05,
                            "estimate": 0.04
                        },
                        {
                            "date": "4Q2023",
                            "actual": 0.06,
                            "estimate": 0.05
                        },
                        {
                            "date": "1Q2024",
                            "actual": 0.05,
                            "estimate": 0.04
                        }
                    ],
                    "currentQuarterEstimate": 0.03,
                    "currentQuarterEstimateDate": "2Q",
                    "currentQuarterEstimateYear": 2024,
                    "earningsDate": [
                        "2024-07-31 19:00:S"
                    ]
                },
                "financialsChart": {
                    "yearly": [
                        {
                            "date": 2020,
                            "revenue": 58378995000,
                            "earnings": 11379394000
                        },
                        {
                            "date": 2021,
                            "revenue": 72854344000,
                            "earnings": 12670968000
                        },
                        {
                            "date": 2022,
                            "revenue": 79708827000,
                            "earnings": 14457943000
                        },
                        {
                            "date": 2023,
                            "revenue": 79736856000,
                            "earnings": 14501944000
                        }
                    ],
                    "quarterly": [
                        {
                            "date": "2Q2023",
                            "revenue": 18898114000,
                            "earnings": 2502974000
                        },
                        {
                            "date": "3Q2023",
                            "revenue": 20317765000,
                            "earnings": 3911740000
                        },
                        {
                            "date": "4Q2023",
                            "revenue": 19989234000,
                            "earnings": 4387655000
                        },
                        {
                            "date": "1Q2024",
                            "revenue": 20276297000,
                            "earnings": 3700276000
                        }
                    ]
                },
                "financialCurrency": "BRL"
            },
            "pageViews": {
                "shortTermTrend": "DOWN",
                "midTermTrend": "UP",
                "longTermTrend": "UP",
                "maxAge": 1
            },
            "financialData": {
                "maxAge": 86400,
                "currentPrice": 2.15,
                "targetHighPrice": 5.0,
                "targetLowPrice": 2.1,
                "targetMeanPrice": 3.16,
                "targetMedianPrice": 3.05,
                "recommendationMean": 2.3,
                "recommendationKey": "buy",
                "numberOfAnalystOpinions": 8,
                "totalCash": 13921714176,
                "totalCashPerShare": 0.884,
                "ebitda": 23240275968,
                "totalDebt": 3817430016,
                "quickRatio": 0.64,
                "currentRatio": 0.993,
                "totalRevenue": 79481413632,
                "debtToEquity": 4.369,
                "revenuePerShare": 5.048,
                "returnOnAssets": 0.087419994,
                "returnOnEquity": 0.17197001,
                "freeCashflow": 12278196224,
                "operatingCashflow": 26005895168,
                "earningsGrowth": 0.0,
                "revenueGrowth": -0.012,
                "grossMargins": 0.50657004,
                "ebitdaMargins": 0.2924,
                "operatingMargins": 0.23945,
                "profitMargins": 0.18247,
                "financialCurrency": "BRL"
            }
        }
    }
}