{
    "CHTR": {
        "triggers": [
            {
                "high_timestamp": "2024-06-18 09:45:00-04:00",
                "high_price": 289.98,
                "trigger_timestamp": "2024-06-18 12:30:00-04:00",
                "trigger_price": 283.03,
                "percentage_drop": 2.4,
                "bar_high": 283.43,
                "bar_low": 283.03,
                "bar_open": 283.18,
                "bar_close": 283.35
            },
            {
                "high_timestamp": "2024-06-24 15:05:00-04:00",
                "high_price": 292.26,
                "trigger_timestamp": "2024-06-25 10:10:00-04:00",
                "trigger_price": 284.86,
                "percentage_drop": 2.53,
                "bar_high": 285.62,
                "bar_low": 284.86,
                "bar_open": 284.89,
                "bar_close": 285.62
            },
            {
                "high_timestamp": "2024-06-28 10:40:00-04:00",
                "high_price": 306.21,
                "trigger_timestamp": "2024-06-28 14:40:00-04:00",
                "trigger_price": 297.61,
                "percentage_drop": 2.81,
                "bar_high": 298.55,
                "bar_low": 297.61,
                "bar_open": 297.61,
                "bar_close": 298.55
            },
            {
                "high_timestamp": "2024-06-28 16:10:00-04:00",
                "high_price": 298.96,
                "trigger_timestamp": "2024-07-01 11:45:00-04:00",
                "trigger_price": 292.39,
                "percentage_drop": 2.2,
                "bar_high": 292.84,
                "bar_low": 292.39,
                "bar_open": 292.84,
                "bar_close": 292.64
            },
            {
                "high_timestamp": "2024-07-02 16:00:00-04:00",
                "high_price": 303.5,
                "trigger_timestamp": "2024-07-08 10:50:00-04:00",
                "trigger_price": 296.91,
                "percentage_drop": 2.17,
                "bar_high": 297.69,
                "bar_low": 296.91,
                "bar_open": 297.27,
                "bar_close": 296.91
            },
            {
                "high_timestamp": "2024-07-08 11:25:00-04:00",
                "high_price": 297.07,
                "trigger_timestamp": "2024-07-08 12:50:00-04:00",
                "trigger_price": 290.18,
                "percentage_drop": 2.32,
                "bar_high": 291.77,
                "bar_low": 290.18,
                "bar_open": 291.76,
                "bar_close": 290.18
            }
        ],
        "trades": [
            {
                "buy_timestamp": "2024-06-18 12:30:00-04:00",
                "buy_price": 283.03,
                "sell_timestamp": "2024-06-21 09:30:00-04:00",
                "sell_price": 289.1,
                "profit": 5.67
            },
            {
                "buy_timestamp": "2024-06-25 10:10:00-04:00",
                "buy_price": 284.86,
                "sell_timestamp": "2024-06-26 09:55:00-04:00",
                "sell_price": 291.33,
                "profit": 5.71
            },
            {
                "buy_timestamp": "2024-06-28 14:40:00-04:00",
                "buy_price": 297.61,
                "sell_timestamp": "2024-06-28 19:15:00-04:00",
                "sell_price": 304.52,
                "profit": 5.97
            },
            {
                "buy_timestamp": "2024-07-01 11:45:00-04:00",
                "buy_price": 292.39,
                "sell_timestamp": "2024-07-02 10:00:00-04:00",
                "sell_price": 298.7,
                "profit": 5.86
            },
            {
                "buy_timestamp": "2024-07-08 10:50:00-04:00",
                "buy_price": 296.91,
                "sell_timestamp": "2024-07-11 15:50:00-04:00",
                "sell_price": 303.64,
                "profit": 5.95
            }
        ],
        "totals": {
            "Report": "Source: Yahoo, Period: 1Mo, Interval: 5Mi",
            "Threshold": 2,
            "Triggers": 6,
            "Buy_Orders": 5,
            "Sell_Orders": 5,
            "Gained": 10,
            "Working_Days": 10,
            "Annual_Trade_Gain": 252.0,
            "Score": 73.22,
            "Updated": "2024-07-15 07:59:55 PM EDT"
        }
    }
}