{
    "CMCSA": {
        "triggers": [
            {
                "high_timestamp": "2024-06-18 09:45:00-04:00",
                "high_price": 37.5,
                "trigger_timestamp": "2024-06-18 13:55:00-04:00",
                "trigger_price": 36.92,
                "percentage_drop": 1.53,
                "bar_high": 36.95,
                "bar_low": 36.92,
                "bar_open": 36.94,
                "bar_close": 36.94
            },
            {
                "high_timestamp": "2024-06-25 05:45:00-04:00",
                "high_price": 38.83,
                "trigger_timestamp": "2024-06-25 10:25:00-04:00",
                "trigger_price": 38.15,
                "percentage_drop": 1.76,
                "bar_high": 38.22,
                "bar_low": 38.15,
                "bar_open": 38.2,
                "bar_close": 38.21
            },
            {
                "high_timestamp": "2024-06-25 17:50:00-04:00",
                "high_price": 38.5,
                "trigger_timestamp": "2024-06-26 14:00:00-04:00",
                "trigger_price": 37.7,
                "percentage_drop": 2.08,
                "bar_high": 37.77,
                "bar_low": 37.7,
                "bar_open": 37.72,
                "bar_close": 37.75
            },
            {
                "high_timestamp": "2024-06-28 10:40:00-04:00",
                "high_price": 39.21,
                "trigger_timestamp": "2024-07-01 11:55:00-04:00",
                "trigger_price": 38.47,
                "percentage_drop": 1.9,
                "bar_high": 38.5,
                "bar_low": 38.47,
                "bar_open": 38.49,
                "bar_close": 38.47
            },
            {
                "high_timestamp": "2024-07-01 14:05:00-04:00",
                "high_price": 38.45,
                "trigger_timestamp": "2024-07-02 11:45:00-04:00",
                "trigger_price": 38.04,
                "percentage_drop": 1.07,
                "bar_high": 38.08,
                "bar_low": 38.04,
                "bar_open": 38.06,
                "bar_close": 38.04
            },
            {
                "high_timestamp": "2024-07-03 12:25:00-04:00",
                "high_price": 38.21,
                "trigger_timestamp": "2024-07-05 11:15:00-04:00",
                "trigger_price": 37.81,
                "percentage_drop": 1.05,
                "bar_high": 37.85,
                "bar_low": 37.81,
                "bar_open": 37.83,
                "bar_close": 37.82
            },
            {
                "high_timestamp": "2024-07-05 15:50:00-04:00",
                "high_price": 37.93,
                "trigger_timestamp": "2024-07-08 12:45:00-04:00",
                "trigger_price": 37.35,
                "percentage_drop": 1.53,
                "bar_high": 37.41,
                "bar_low": 37.35,
                "bar_open": 37.4,
                "bar_close": 37.36
            },
            {
                "high_timestamp": "2024-07-09 19:40:00-04:00",
                "high_price": 37.73,
                "trigger_timestamp": "2024-07-10 10:35:00-04:00",
                "trigger_price": 37.3,
                "percentage_drop": 1.14,
                "bar_high": 37.38,
                "bar_low": 37.3,
                "bar_open": 37.31,
                "bar_close": 37.37
            }
        ],
        "trades": [
            {
                "buy_timestamp": "2024-06-18 13:55:00-04:00",
                "buy_price": 36.92,
                "sell_timestamp": "2024-06-20 10:15:00-04:00",
                "sell_price": 37.32,
                "profit": 0.37
            },
            {
                "buy_timestamp": "2024-06-25 10:25:00-04:00",
                "buy_price": 38.15,
                "sell_timestamp": "2024-06-25 17:30:00-04:00",
                "sell_price": 38.6,
                "profit": 0.38
            },
            {
                "buy_timestamp": "2024-06-26 14:00:00-04:00",
                "buy_price": 37.7,
                "sell_timestamp": "2024-06-26 15:20:00-04:00",
                "sell_price": 38.15,
                "profit": 0.38
            },
            {
                "buy_timestamp": "2024-07-01 11:55:00-04:00",
                "buy_price": 38.47,
                "sell_timestamp": "2024-07-15 10:15:00-04:00",
                "sell_price": 38.88,
                "profit": 0.38
            }
        ],
        "totals": {
            "Report": "Source: Yahoo, Period: 1Mo, Interval: 5Mi",
            "Threshold": 1,
            "Triggers": 8,
            "Buy_Orders": 4,
            "Sell_Orders": 4,
            "Gained": 4,
            "Working_Days": 14,
            "Annual_Trade_Gain": 72.0,
            "Score": 5.09,
            "Updated": "2024-07-15 07:07:52 PM EDT"
        }
    }
}