{
    "MLTX": {
        "triggers": [],
        "trades": [],
        "totals": {
            "Start_Date": "2020-11-01",
            "Start_Price": 10.4,
            "Current_Price": 48.56,
            "Overall_Trend": "Upward",
            "Average_Monthly_Change": 5.01,
            "Average_APR": 52.25,
            "Highest_High": 64.98,
            "Current_High": 48.96,
            "High_To_Highest_Ratio": 0.75,
            "Forward_PE_Ratio": -24.65,
            "Recommendation": "Buy",
            "Month_Inflow": 5676407.23,
            "Month_Outflow": 2871059.87,
            "Month_Net": 2805347.36,
            "50_200_MA_Trend": -7.3,
            "Risk": 5,
            "Score": 2111.8,
            "Updated": "2024-07-15 03:54:02 PM EDT"
        }
    }
}