{
    "TSLA": {
        "triggers": [],
        "trades": [],
        "totals": {
            "Start_Date": "2010-07-01",
            "Start_Price": 1.33,
            "Current_Price": 252.64,
            "Overall_Trend": "Upward",
            "Average_Monthly_Change": 4.24,
            "Average_APR": 45.42,
            "Highest_High": 414.5,
            "Current_High": 271.0,
            "High_To_Highest_Ratio": 0.65,
            "Trailing_PE_Ratio": 64.45,
            "Forward_PE_Ratio": 75.41,
            "PEG_Ratio": 6.26,
            "PS_Ratio": 8.5,
            "Recommendation": "Hold",
            "Month_Inflow": 14302658682.51,
            "Month_Outflow": 5317074247.76,
            "Month_Net": 8985584434.75,
            "50_200_MA_Trend": -12.67,
            "Risk": 10,
            "Score": 689.66,
            "Updated": "2024-07-15 11:25:59 PM EDT"
        }
    }
}